llmFunctionDecorator/__init__.py
llmFunctionDecorator-1.0.0.dist-info/METADATA
llmFunctionDecorator-1.0.0.dist-info/WHEEL
llmFunctionDecorator-1.0.0.dist-info/top_level.txt
llmFunctionDecorator-1.0.0.dist-info/RECORD
