Metadata-Version: 2.1
Name: llmFunctionDecorator
Version: 1.0.0
Summary: A simplified function decorator for OpenAI and LiteLLM API calls.
Home-page: https://github.com/A-M-D-R-3-W/llmFunctionDecorator/
Author: A-M-D-R-3-W
Author-email: AMDR3W@proton.me
License: MIT
Project-URL: Documentation, https://github.com/A-M-D-R-3-W/llmFunctionDecorator/blob/main/README.md
Project-URL: Source, https://github.com/A-M-D-R-3-W/llmFunctionDecorator/
Classifier: Programming Language :: Python :: 3
Classifier: License :: OSI Approved :: MIT License
Classifier: Operating System :: OS Independent
Classifier: Intended Audience :: Developers
Classifier: Topic :: Software Development :: Libraries :: Python Modules
Classifier: Programming Language :: Python :: 3.8
Classifier: Programming Language :: Python :: 3.9
Classifier: Programming Language :: Python :: 3.10
Classifier: Programming Language :: Python :: 3.11
Classifier: Programming Language :: Python :: 3.12
Classifier: Topic :: Scientific/Engineering :: Artificial Intelligence
Classifier: Development Status :: 4 - Beta
Classifier: Topic :: Utilities
Requires-Python: >=3.8
